<?xml version="1.0" encoding="UTF-8"?>
<buildings>

	<building id="1">
		
		<name>SpongeBob's Pineapple</name>
		<asset>spongebobs_pineapple</asset>
		<hit_area x="20" y="-100" w="250" h="240"></hit_area>
		<anchor x="190" y="480"></anchor>
		
   </building>

   <building id="2">
		
		<name>The Krusty Krab</name>
		<asset>krusty_krab</asset>
		<hit_area x="0" y="-160" w="640" h="330"></hit_area>
		<anchor x="328" y="504"></anchor>
		
   </building>

   <building id="3">
		
		<name>Patrick's Stone</name>
		<asset>patricks_stone</asset>
		<hit_area x="0" y="-60" w="280" h="120"></hit_area>
		<anchor x="206" y="302"></anchor>
		
   </building>

   <building id="4">
		
		<name>Squidward's House</name>
		<asset>squidwards_house</asset>
		<hit_area x="0" y="-80" w="300" h="200"></hit_area>
		<anchor x="168" y="562"></anchor>
		
   </building>

   <building id="5">
	
		<name>Sandy's Treedome</name>
		<asset>sandys_treedome</asset>
		<hit_area x="0" y="-165" w="580" h="340"></hit_area>
		<anchor x="296" y="530"></anchor>
		
   </building>

   <building id="6">
		
		<name>Mr. Krabs' Anchor</name>
		<asset>mr_krabs_anchor</asset>
		<hit_area x="0" y="-60" w="680" h="120"></hit_area>
		<anchor x="348" y="602"></anchor>
		
   </building>

   <building id="7">
		
		<name>The Chum Bucket</name>
		<asset>chum_bucket</asset>
		<hit_area x="0" y="-120" w="375" h="250"></hit_area>
		<anchor x="248" y="662"></anchor>
		
   </building>

   <building id="8">
		
		<name>Hospital</name>
		<asset>hospital</asset>
		<hit_area x="10" y="-160" w="730" h="400"></hit_area>
		<anchor x="470" y="646"></anchor>
		
   </building>

   <building id="9">
		
		<name>Krusty Krab Sign</name>
		<asset>krusty_krab_sign</asset>
		<hit_area x="0" y="0" w="20" h="20"></hit_area>
		<anchor x="50" y="352"></anchor>
		
   </building>

   <building id="10">
		
		<name>Misc. House</name>
		<asset>house</asset>
		<hit_area x="20" y="-10" w="150" h="80"></hit_area>
		<anchor x="204" y="602"></anchor>
		
   </building>

   <building id="11">
		
		<name>Sandy's Treedome Entrance</name>
		<asset>sandys_treedome_entrance</asset>
		<hit_area x="0" y="-125" w="120" h="225"></hit_area>
		<anchor x="56" y="245"></anchor>
		
   </building>

   <building id="12">
		
		<name>Statue</name>
		<asset>statue</asset>
		<hit_area x="3" y="-40" w="180" h="120"></hit_area>
		<anchor x="192" y="400"></anchor>
		
   </building>
   
</buildings>