{"frameRate":30,"movies":[{"layers":[{"name":"bottom","keyframes":[{"ease":1,"duration":11,"index":0,"ref":"bottom","pivot":[512,230.75],"loc":[833.625,735.7]},{"duration":4,"pivot":[512,230.75],"index":11,"ref":"bottom","loc":[512.025,369.225]},{"ease":1,"duration":14,"index":15,"ref":"bottom","pivot":[512,230.75],"loc":[512.025,369.225]},{"duration":1,"pivot":[512,230.75],"index":29,"ref":"bottom","loc":[-513.65,682.325]}]},{"name":"top","keyframes":[{"ease":1,"duration":11,"index":0,"ref":"top","pivot":[512,228.75],"loc":[151.125,-135.175]},{"duration":4,"pivot":[512,228.75],"index":11,"ref":"top","loc":[512,228.775]},{"ease":1,"duration":14,"index":15,"ref":"top","pivot":[512,228.75],"loc":[512,228.775]},{"duration":1,"pivot":[512,228.75],"index":29,"ref":"top","loc":[1537.1,-91.05]}]}],"id":"transition"}],"md5":"8d300708e9b116dd3b75801251d5e452","atlases":[{"textures":[{"rect":[0,0,1024,462],"offset":[0,0],"symbol":"bottom"}],"file":"atlas0.png"},{"textures":[{"rect":[0,0,1024,458],"offset":[0,0],"symbol":"top"}],"file":"atlas1.png"}]}